mwePyPI/__init__.py
mwePyPI/file_with_mysum.py
mwePyPI-0.0.2.dist-info/DESCRIPTION.rst
mwePyPI-0.0.2.dist-info/METADATA
mwePyPI-0.0.2.dist-info/RECORD
mwePyPI-0.0.2.dist-info/WHEEL
mwePyPI-0.0.2.dist-info/metadata.json
mwePyPI-0.0.2.dist-info/top_level.txt
