Metadata-Version: 2.0
Name: mwePyPI
Version: 0.0.2
Summary: It is a minimal work exemple of a package to be uploaded in PyPI.
Home-page: https://github.com/PedroRegisPOAR/mwePyPi
Author: Pedro Osvaldo Alencar Regis
Author-email: pedroalencarregis@hotmail.com
License: MIT
Platform: UNKNOWN
